django_reports_creator-0.0.2.dist-info/METADATA
django_reports_creator-0.0.2.dist-info/RECORD
django_reports_creator-0.0.2.dist-info/WHEEL
django_reports_creator-0.0.2.dist-info/top_level.txt
reports_creator/__init__.py
reports_creator/arial10.py
reports_creator/export_pdf.py
reports_creator/forms.py
reports_creator/report.py
reports_creator/urls.py
reports_creator/utils.py
reports_creator/views.py
reports_creator/widgets.py
reports_creator/exporters/__init__.py
reports_creator/exporters/base.py
reports_creator/exporters/excel.py
reports_creator/exporters/pdf.py
reports_creator/highcharts/__init__.py
reports_creator/highcharts/base.py
reports_creator/highcharts/options.py
reports_creator/templatetags/__init__.py
reports_creator/templatetags/model_report.py
